PythonJsonEditorWindow/PythonJsonEditorWindow.py
PythonJsonEditorWindow/__init__.py
PythonJsonEditorWindow-0.0.5.dist-info/LICENSE
PythonJsonEditorWindow-0.0.5.dist-info/METADATA
PythonJsonEditorWindow-0.0.5.dist-info/WHEEL
PythonJsonEditorWindow-0.0.5.dist-info/top_level.txt
PythonJsonEditorWindow-0.0.5.dist-info/RECORD
