Metadata-Version: 2.1
Name: PythonJsonEditorWindow
Version: 0.0.5
Summary: A GUI window for editing JSON files using Python.
Home-page: https://github.com/starikcetin/PythonJsonEditorWindow
Author: starikcetin <cetinsamedtarik@gmail.com> (https://github.com/starikcetin)
Author-email: cetinsamedtarik@gmail.com
License: UNKNOWN
Keywords: python json editor window gui ui
Platform: UNKNOWN
Classifier: Programming Language :: Python :: 3
Classifier: License :: OSI Approved :: MIT License
Classifier: Operating System :: OS Independent
Requires-Dist: pysimplegui
